LICENSE
README.md
lognormcl.py
pyproject.toml
setup.cfg
setup.py
lognormcl.egg-info/PKG-INFO
lognormcl.egg-info/SOURCES.txt
lognormcl.egg-info/dependency_links.txt
lognormcl.egg-info/requires.txt
lognormcl.egg-info/top_level.txt