Metadata-Version: 2.1
Name: lognormcl
Version: 2021.4.20
Summary: angular power spectra of lognormal random fields
Home-page: https://github.com/ntessore/lognormcl
Maintainer: Nicolas Tessore
Maintainer-email: n.tessore@ucl.ac.uk
License: MIT
Project-URL: Documentation, https://cltools.readthedocs.io/lognormcl/
Platform: UNKNOWN
Classifier: Programming Language :: Python :: 3
Classifier: License :: OSI Approved :: MIT License
Classifier: Operating System :: OS Independent
Requires-Python: >=3.6
